python_worker_extension/__init__.py
tracer_extension-1.0.32.dist-info/METADATA
tracer_extension-1.0.32.dist-info/WHEEL
tracer_extension-1.0.32.dist-info/top_level.txt
tracer_extension-1.0.32.dist-info/RECORD
