Metadata-Version: 2.1
Name: tracer-extension
Version: 1.0.32
Summary: Python Worker Extension for starting Datadog Tracer and a top level span to enable auto-instrumenting of Azure Function Apps
Author: Gordon
Author-email: gordon.hamilton@datadoghq.com
Requires-Dist: azure-functions <2.0.0,>=1.7.0
Requires-Dist: ddtrace
